README.md
setup.py
featurefilter/__init__.py
featurefilter/abstract_transformer.py
featurefilter/feature_correlation_filter.py
featurefilter/glm_filter.py
featurefilter/na_filter.py
featurefilter/sklearn_wrapper.py
featurefilter/target_correlation_filter.py
featurefilter/tree_based_filter.py
featurefilter/variance_filter.py
featurefilter.egg-info/PKG-INFO
featurefilter.egg-info/SOURCES.txt
featurefilter.egg-info/dependency_links.txt
featurefilter.egg-info/not-zip-safe
featurefilter.egg-info/requires.txt
featurefilter.egg-info/top_level.txt